{
	"name": "SalesOutPutUNI",
	"properties": {
		"linkedServiceName": {
			"referenceName": "HomeBlobStorage",
			"type": "LinkedServiceReference"
		},
		"annotations": [],
		"type": "DelimitedText",
		"typeProperties": {
			"location": {
				"type": "AzureBlobStorageLocation",
				"folderPath": "SalesOutPutData",
				"container": "adfdemo"
			},
			"columnDelimiter": ",",
			"escapeChar": "\\",
			"quoteChar": "\""
		},
		"schema": [
			{
				"type": "String"
			},
			{
				"type": "String"
			}
		]
	}
}